jsontextmc/__init__.py
jsontextmc-3.2.0.dist-info/LICENSE.txt
jsontextmc-3.2.0.dist-info/METADATA
jsontextmc-3.2.0.dist-info/WHEEL
jsontextmc-3.2.0.dist-info/top_level.txt
jsontextmc-3.2.0.dist-info/RECORD
