Metadata-Version: 2.1
Name: jsontextmc
Version: 3.2.0
Summary: Tool to translate old Minecraft formatting codes to the modern JSON format
Author: WhoAteMyButter
License: GPL-3.0-or-later
Project-URL: Source, https://gitlab.com/whoatembutter/jsontextmc
Project-URL: Changelog, https://gitlab.com/whoatemybutter/jsontextmc/-/blob/master/CHANGELOG.md
Keywords: minecraft,fonts,minecraft fonts,font exporting,minecraft opentype,minecraft font,minecraft export font,mc font,mc fonts,mcfonts
Classifier: Programming Language :: Python :: 3
Classifier: Programming Language :: Python :: 3 :: Only
Classifier: Operating System :: OS Independent
Classifier: Topic :: Software Development :: Localization
Classifier: Topic :: Text Processing :: General
Classifier: Topic :: Utilities
Classifier: Topic :: Games/Entertainment :: Simulation
Classifier: Development Status :: 5 - Production/Stable
Classifier: License :: OSI Approved :: GNU General Public License v3 (GPLv3)
Classifier: Natural Language :: English
Classifier: Operating System :: OS Independent
Classifier: Topic :: Text Processing
Classifier: Topic :: Text Processing :: Indexing
Requires-Python: >=3.10
License-File: LICENSE.txt
